[
  {
    "venue_id": "venue_mercedes_benz_stadium",
    "venue_name": "Mercedes-Benz Stadium",
    "tournament_name": "Atlanta Stadium",
    "host_city": "Atlanta",
    "city": "Atlanta",
    "country": "United States",
    "latitude": 33.7554123,
    "longitude": -84.4008493,
    "altitude_m": null,
    "capacity": null,
    "pitch_type": null,
    "roof_type": null,
    "source": "fifa_official_stadiums_and_openstreetmap_nominatim",
    "source_url": "https://www.fifa.com/en/tournaments/mens/worldcup/canadamexicousa2026/stadiums",
    "coordinate_source_url": "https://nominatim.openstreetmap.org/search?format=json&limit=1&q=Mercedes-Benz%20Stadium%20Atlanta%20Georgia",
    "source_venue_ids": ["SportRadar_Soccer_InternationalWorldCup_2026_Venue_20343"],
    "aliases": ["Atlanta Stadium", "Mercedes-Benz Stadium"]
  },
  {
    "venue_id": "venue_gillette_stadium",
    "venue_name": "Gillette Stadium",
    "tournament_name": "Boston Stadium",
    "host_city": "Boston",
    "city": "Foxborough",
    "country": "United States",
    "latitude": 42.0908879,
    "longitude": -71.2641731,
    "altitude_m": null,
    "capacity": null,
    "pitch_type": null,
    "roof_type": null,
    "source": "fifa_official_stadiums_and_openstreetmap_nominatim",
    "source_url": "https://www.fifa.com/en/tournaments/mens/worldcup/canadamexicousa2026/stadiums",
    "coordinate_source_url": "https://nominatim.openstreetmap.org/search?format=json&limit=1&q=Gillette%20Stadium%20Foxborough%20Massachusetts",
    "source_venue_ids": ["SportRadar_Soccer_InternationalWorldCup_2026_Venue_2379"],
    "aliases": ["Boston Stadium", "Gillette Stadium"]
  },
  {
    "venue_id": "venue_att_stadium",
    "venue_name": "AT&T Stadium",
    "tournament_name": "Dallas Stadium",
    "host_city": "Dallas",
    "city": "Arlington",
    "country": "United States",
    "latitude": 32.7478503,
    "longitude": -97.0928337,
    "altitude_m": null,
    "capacity": null,
    "pitch_type": null,
    "roof_type": null,
    "source": "fifa_official_stadiums_and_openstreetmap_nominatim",
    "source_url": "https://www.fifa.com/en/tournaments/mens/worldcup/canadamexicousa2026/stadiums",
    "coordinate_source_url": "https://nominatim.openstreetmap.org/search?format=json&limit=1&q=AT%26T%20Stadium%20Arlington%20Texas",
    "source_venue_ids": ["SportRadar_Soccer_InternationalWorldCup_2026_Venue_6650"],
    "aliases": ["Dallas Stadium", "AT&T Stadium", "ATT Stadium"]
  },
  {
    "venue_id": "venue_estadio_akron",
    "venue_name": "Estadio Akron",
    "tournament_name": "Guadalajara Stadium",
    "host_city": "Guadalajara",
    "city": "Zapopan",
    "country": "Mexico",
    "latitude": 20.6818469,
    "longitude": -103.4626718,
    "altitude_m": null,
    "capacity": null,
    "pitch_type": null,
    "roof_type": null,
    "source": "fifa_official_stadiums_and_openstreetmap_nominatim",
    "source_url": "https://www.fifa.com/en/tournaments/mens/worldcup/canadamexicousa2026/stadiums",
    "coordinate_source_url": "https://nominatim.openstreetmap.org/search?format=json&limit=1&q=Estadio%20Akron%20Zapopan%20Jalisco",
    "source_venue_ids": ["SportRadar_Soccer_InternationalWorldCup_2026_Venue_2401"],
    "aliases": ["Guadalajara Stadium", "Estadio Guadalajara", "Estadio Akron"]
  },
  {
    "venue_id": "venue_nrg_stadium",
    "venue_name": "NRG Stadium",
    "tournament_name": "Houston Stadium",
    "host_city": "Houston",
    "city": "Houston",
    "country": "United States",
    "latitude": 29.6848581,
    "longitude": -95.4108015,
    "altitude_m": null,
    "capacity": null,
    "pitch_type": null,
    "roof_type": null,
    "source": "fifa_official_stadiums_and_openstreetmap_nominatim",
    "source_url": "https://www.fifa.com/en/tournaments/mens/worldcup/canadamexicousa2026/stadiums",
    "coordinate_source_url": "https://nominatim.openstreetmap.org/search?format=json&limit=1&q=NRG%20Stadium%20Houston%20Texas",
    "source_venue_ids": ["SportRadar_Soccer_InternationalWorldCup_2026_Venue_2402"],
    "aliases": ["Houston Stadium", "NRG Stadium"]
  },
  {
    "venue_id": "venue_arrowhead_stadium",
    "venue_name": "Arrowhead Stadium",
    "tournament_name": "Kansas City Stadium",
    "host_city": "Kansas City",
    "city": "Kansas City",
    "country": "United States",
    "latitude": 39.0489358,
    "longitude": -94.4839993,
    "altitude_m": null,
    "capacity": null,
    "pitch_type": null,
    "roof_type": null,
    "source": "fifa_official_stadiums_and_openstreetmap_nominatim",
    "source_url": "https://www.fifa.com/en/tournaments/mens/worldcup/canadamexicousa2026/stadiums",
    "coordinate_source_url": "https://nominatim.openstreetmap.org/search?format=json&limit=1&q=Arrowhead%20Stadium%20Kansas%20City%20Missouri",
    "source_venue_ids": ["SportRadar_Soccer_InternationalWorldCup_2026_Venue_8189"],
    "aliases": ["Kansas City Stadium", "Arrowhead Stadium"]
  },
  {
    "venue_id": "venue_sofi_stadium",
    "venue_name": "SoFi Stadium",
    "tournament_name": "Los Angeles Stadium",
    "host_city": "Los Angeles",
    "city": "Inglewood",
    "country": "United States",
    "latitude": 33.9534074,
    "longitude": -118.3390098,
    "altitude_m": null,
    "capacity": null,
    "pitch_type": null,
    "roof_type": null,
    "source": "fifa_official_stadiums_and_openstreetmap_nominatim",
    "source_url": "https://www.fifa.com/en/tournaments/mens/worldcup/canadamexicousa2026/stadiums",
    "coordinate_source_url": "https://nominatim.openstreetmap.org/search?format=json&limit=1&q=SoFi%20Stadium%20Inglewood%20California",
    "source_venue_ids": ["SportRadar_Soccer_InternationalWorldCup_2026_Venue_52183"],
    "aliases": ["Los Angeles Stadium", "SoFi Stadium"]
  },
  {
    "venue_id": "venue_estadio_azteca",
    "venue_name": "Estadio Azteca",
    "tournament_name": "Mexico City Stadium",
    "host_city": "Mexico City",
    "city": "Mexico City",
    "country": "Mexico",
    "latitude": 19.3029794,
    "longitude": -99.15047,
    "altitude_m": null,
    "capacity": null,
    "pitch_type": null,
    "roof_type": null,
    "source": "fifa_official_stadiums_and_openstreetmap_nominatim",
    "source_url": "https://www.fifa.com/en/tournaments/mens/worldcup/canadamexicousa2026/stadiums",
    "coordinate_source_url": "https://nominatim.openstreetmap.org/search?format=json&limit=1&q=Estadio%20Azteca%20Mexico%20City",
    "source_venue_ids": ["SportRadar_Soccer_InternationalWorldCup_2026_Venue_1004"],
    "aliases": ["Mexico City Stadium", "Estadio Azteca", "Estadio Banorte"]
  },
  {
    "venue_id": "venue_hard_rock_stadium",
    "venue_name": "Hard Rock Stadium",
    "tournament_name": "Miami Stadium",
    "host_city": "Miami",
    "city": "Miami Gardens",
    "country": "United States",
    "latitude": 25.9579032,
    "longitude": -80.2388497,
    "altitude_m": null,
    "capacity": null,
    "pitch_type": null,
    "roof_type": null,
    "source": "fifa_official_stadiums_and_openstreetmap_nominatim",
    "source_url": "https://www.fifa.com/en/tournaments/mens/worldcup/canadamexicousa2026/stadiums",
    "coordinate_source_url": "https://nominatim.openstreetmap.org/search?format=json&limit=1&q=Hard%20Rock%20Stadium%20Miami%20Gardens%20Florida",
    "source_venue_ids": ["SportRadar_Soccer_InternationalWorldCup_2026_Venue_21306"],
    "aliases": ["Miami Stadium", "Hard Rock Stadium"]
  },
  {
    "venue_id": "venue_estadio_bbva",
    "venue_name": "Estadio BBVA",
    "tournament_name": "Monterrey Stadium",
    "host_city": "Monterrey",
    "city": "Guadalupe",
    "country": "Mexico",
    "latitude": 25.6691106,
    "longitude": -100.2444506,
    "altitude_m": null,
    "capacity": null,
    "pitch_type": null,
    "roof_type": null,
    "source": "fifa_official_stadiums_and_openstreetmap_nominatim",
    "source_url": "https://www.fifa.com/en/tournaments/mens/worldcup/canadamexicousa2026/stadiums",
    "coordinate_source_url": "https://nominatim.openstreetmap.org/search?format=json&limit=1&q=Estadio%20BBVA%20Guadalupe%20Nuevo%20Leon",
    "source_venue_ids": ["SportRadar_Soccer_InternationalWorldCup_2026_Venue_16526"],
    "aliases": ["Monterrey Stadium", "Estadio Monterrey", "Estadio BBVA"]
  },
  {
    "venue_id": "venue_metlife_stadium",
    "venue_name": "MetLife Stadium",
    "tournament_name": "New York New Jersey Stadium",
    "host_city": "New York/New Jersey",
    "city": "East Rutherford",
    "country": "United States",
    "latitude": 40.8135071,
    "longitude": -74.0743442,
    "altitude_m": null,
    "capacity": null,
    "pitch_type": null,
    "roof_type": null,
    "source": "fifa_official_stadiums_and_openstreetmap_nominatim",
    "source_url": "https://www.fifa.com/en/tournaments/mens/worldcup/canadamexicousa2026/stadiums",
    "coordinate_source_url": "https://nominatim.openstreetmap.org/search?format=json&limit=1&q=MetLife%20Stadium%20East%20Rutherford%20New%20Jersey",
    "source_venue_ids": ["SportRadar_Soccer_InternationalWorldCup_2026_Venue_1981"],
    "aliases": ["New York New Jersey Stadium", "MetLife Stadium"]
  },
  {
    "venue_id": "venue_lincoln_financial_field",
    "venue_name": "Lincoln Financial Field",
    "tournament_name": "Philadelphia Stadium",
    "host_city": "Philadelphia",
    "city": "Philadelphia",
    "country": "United States",
    "latitude": 39.9009099,
    "longitude": -75.1674892,
    "altitude_m": null,
    "capacity": null,
    "pitch_type": null,
    "roof_type": null,
    "source": "fifa_official_stadiums_and_openstreetmap_nominatim",
    "source_url": "https://www.fifa.com/en/tournaments/mens/worldcup/canadamexicousa2026/stadiums",
    "coordinate_source_url": "https://nominatim.openstreetmap.org/search?format=json&limit=1&q=Lincoln%20Financial%20Field%20Philadelphia%20Pennsylvania",
    "source_venue_ids": ["SportRadar_Soccer_InternationalWorldCup_2026_Venue_1833"],
    "aliases": ["Philadelphia Stadium", "Lincoln Financial Field"]
  },
  {
    "venue_id": "venue_levis_stadium",
    "venue_name": "Levi's Stadium",
    "tournament_name": "San Francisco Bay Area Stadium",
    "host_city": "San Francisco Bay Area",
    "city": "Santa Clara",
    "country": "United States",
    "latitude": 37.4029867,
    "longitude": -121.9696489,
    "altitude_m": null,
    "capacity": null,
    "pitch_type": null,
    "roof_type": null,
    "source": "fifa_official_stadiums_and_openstreetmap_nominatim",
    "source_url": "https://www.fifa.com/en/tournaments/mens/worldcup/canadamexicousa2026/stadiums",
    "coordinate_source_url": "https://nominatim.openstreetmap.org/search?format=json&limit=1&q=Levi%27s%20Stadium%20Santa%20Clara%20California",
    "source_venue_ids": ["SportRadar_Soccer_InternationalWorldCup_2026_Venue_15672"],
    "aliases": ["San Francisco Bay Area Stadium", "Levi's Stadium", "Levis Stadium"]
  },
  {
    "venue_id": "venue_lumen_field",
    "venue_name": "Lumen Field",
    "tournament_name": "Seattle Stadium",
    "host_city": "Seattle",
    "city": "Seattle",
    "country": "United States",
    "latitude": 47.5953459,
    "longitude": -122.3316443,
    "altitude_m": null,
    "capacity": null,
    "pitch_type": null,
    "roof_type": null,
    "source": "fifa_official_stadiums_and_openstreetmap_nominatim",
    "source_url": "https://www.fifa.com/en/tournaments/mens/worldcup/canadamexicousa2026/stadiums",
    "coordinate_source_url": "https://nominatim.openstreetmap.org/search?format=json&limit=1&q=Lumen%20Field%20Seattle%20Washington",
    "source_venue_ids": ["SportRadar_Soccer_InternationalWorldCup_2026_Venue_2291"],
    "aliases": ["Seattle Stadium", "Lumen Field"]
  },
  {
    "venue_id": "venue_bmo_field",
    "venue_name": "BMO Field",
    "tournament_name": "Toronto Stadium",
    "host_city": "Toronto",
    "city": "Toronto",
    "country": "Canada",
    "latitude": 43.6333414,
    "longitude": -79.4185614,
    "altitude_m": null,
    "capacity": null,
    "pitch_type": null,
    "roof_type": null,
    "source": "fifa_official_stadiums_and_openstreetmap_nominatim",
    "source_url": "https://www.fifa.com/en/tournaments/mens/worldcup/canadamexicousa2026/stadiums",
    "coordinate_source_url": "https://nominatim.openstreetmap.org/search?format=json&limit=1&q=BMO%20Field%20Toronto%20Ontario",
    "source_venue_ids": ["SportRadar_Soccer_InternationalWorldCup_2026_Venue_2294"],
    "aliases": ["Toronto Stadium", "BMO Field"]
  },
  {
    "venue_id": "venue_bc_place",
    "venue_name": "BC Place",
    "tournament_name": "Vancouver Stadium",
    "host_city": "Vancouver",
    "city": "Vancouver",
    "country": "Canada",
    "latitude": 49.2766905,
    "longitude": -123.1120062,
    "altitude_m": null,
    "capacity": null,
    "pitch_type": null,
    "roof_type": null,
    "source": "fifa_official_stadiums_and_openstreetmap_nominatim",
    "source_url": "https://www.fifa.com/en/tournaments/mens/worldcup/canadamexicousa2026/stadiums",
    "coordinate_source_url": "https://nominatim.openstreetmap.org/search?format=json&limit=1&q=BC%20Place%20Vancouver%20British%20Columbia",
    "source_venue_ids": ["SportRadar_Soccer_InternationalWorldCup_2026_Venue_2293"],
    "aliases": ["Vancouver Stadium", "BC Place", "BC Place Vancouver"]
  }
]
